typingx/__init__.py
typingx/func_check.py
typingx/main.py
typingx/py.typed
typingx/types.py
typingx/typing_compat.py
typingx-0.6.0.dist-info/LICENSE
typingx-0.6.0.dist-info/WHEEL
typingx-0.6.0.dist-info/METADATA
typingx-0.6.0.dist-info/RECORD
